drdk_api/__init__.py
drdk_api/constants.py
drdk_api/objects.py
drdk_api/util.py
drdk_api-0.1.2.dist-info/METADATA
drdk_api-0.1.2.dist-info/WHEEL
drdk_api-0.1.2.dist-info/licenses/LICENSE
drdk_api-0.1.2.dist-info/RECORD
